portl/__init__.py
portl/cli.py
portl/template.yaml
portl/commands/__init__.py
portl/commands/init_command.py
portl/commands/run_command.py
portl/services/__init__.py
portl/services/job_runner.py
portl/services/template_service.py
portl/ui/__init__.py
portl/ui/console.py
portl-0.0.2.dist-info/licenses/LICENSE
portl-0.0.2.dist-info/METADATA
portl-0.0.2.dist-info/WHEEL
portl-0.0.2.dist-info/entry_points.txt
portl-0.0.2.dist-info/top_level.txt
portl-0.0.2.dist-info/RECORD
