Metadata-Version: 2.4
Name: portl
Version: 0.0.2
Summary: A developer-first CLI tool for moving data across databases, CSVs, and Google Sheets
Author-email: Heba Ghazali <hebbaghazali@gmail.com>
License: MIT
Project-URL: Homepage, https://github.com/yourusername/portl
Project-URL: Documentation, https://github.com/yourusername/portl#readme
Project-URL: Repository, https://github.com/yourusername/portl
Project-URL: Issues, https://github.com/yourusername/portl/issues
Keywords: data,migration,database,cli,etl,csv,postgres,mysql,google-sheets
Classifier: Development Status :: 3 - Alpha
Classifier: Intended Audience :: Developers
Classifier: License :: OSI Approved :: MIT License
Classifier: Programming Language :: Python :: 3
Classifier: Programming Language :: Python :: 3.10
Classifier: Programming Language :: Python :: 3.11
Classifier: Programming Language :: Python :: 3.12
Classifier: Topic :: Database
Classifier: Topic :: Software Development :: Libraries :: Python Modules
Classifier: Topic :: System :: Archiving
Requires-Python: >=3.10
License-File: LICENSE
Requires-Dist: click>=8.0.0
Requires-Dist: typer>=0.9.0
Requires-Dist: pyyaml>=6.0
Requires-Dist: psycopg2-binary>=2.9.0
Requires-Dist: pymysql>=1.0.0
Requires-Dist: pandas>=2.0.0
Requires-Dist: google-api-python-client>=2.0.0
Requires-Dist: rich>=13.0.0
Provides-Extra: dev
Requires-Dist: pytest>=7.0.0; extra == "dev"
Requires-Dist: pytest-cov>=4.0.0; extra == "dev"
Requires-Dist: black>=22.0.0; extra == "dev"
Requires-Dist: flake8>=5.0.0; extra == "dev"
Requires-Dist: mypy>=1.0.0; extra == "dev"
Dynamic: license-file
